{
  "$schema": "http://schema.management.azure.com/schemas/2015-01-01/deploymentParameters.json#",
  "contentVersion": "1.0.0.0",
  "parameters": {
    "input": {
      "value": {
        "Id": "/providers/Microsoft.Management/managementGroups/mg-COFT6/providers/Microsoft.Authorization/roleDefinitions/3c2b0b3b-e0a0-5cb3-9a84-06dc0d964ae8",
        "Name": "3c2b0b3b-e0a0-5cb3-9a84-06dc0d964ae8",
        "properties": {
          "assignableScopes": [
            "/providers/Microsoft.Management/managementGroups/mg-COFT6"
          ],
          "description": "Vmware Solution Administrator",
          "permissions": [
            {
              "actions": [
                "Microsoft.Insights/*",
                "Microsoft.Automation/automationAccounts/*",
                "Microsoft.Resources/subscriptions/resourceGroups/read",
                "Microsoft.Management/managementGroups/read",
                "Microsoft.Support/*"
              ],
              "dataActions": [],
              "notActions": [],
              "notdataActions": []
            }
          ],
          "roleName": "rbac-ass-COFT6-IT-prod-Custom Vmware Solution Administrator"
        },
        "ResourceType": "Microsoft.Authorization/roleDefinitions"
      }
    }
  }
}
