{
  "$schema": "http://schema.management.azure.com/schemas/2015-01-01/deploymentParameters.json#",
  "contentVersion": "1.0.0.0",
  "parameters": {
    "input": {
      "value": {
        "Id": "/providers/Microsoft.Management/managementGroups/mg-COFT14/providers/Microsoft.Authorization/roleDefinitions/bcb5b527-6b81-552b-bc46-589804d2021e",
        "Name": "bcb5b527-6b81-552b-bc46-589804d2021e",
        "properties": {
          "assignableScopes": [
            "/providers/Microsoft.Management/managementGroups/mg-COFT14"
          ],
          "description": "Landing Zone Contributor",
          "permissions": [
            {
              "actions": [
                "Microsoft.Authorization/*/Delete",
                "Microsoft.Authorization/*/Write",
                "Microsoft.Authorization/elevateAccess/Action",
                "Microsoft.Blueprint/blueprintAssignments/write",
                "Microsoft.Blueprint/blueprintAssignments/delete",
                "Microsoft.Compute/galleries/share/action",
                "Microsoft.Support/*"
              ],
              "dataActions": [],
              "notActions": [],
              "notdataActions": []
            }
          ],
          "roleName": "rbac-ass-COFT14-IT-prod-Custom Landing Zone Contributor"
        },
        "ResourceType": "Microsoft.Authorization/roleDefinitions"
      }
    }
  }
}
