{
  "$schema": "http://schema.management.azure.com/schemas/2015-01-01/deploymentParameters.json#",
  "contentVersion": "1.0.0.0",
  "parameters": {
    "input": {
      "value": {
        "Id": "/providers/Microsoft.Management/managementGroups/mg-oqlf3/providers/Microsoft.Authorization/roleDefinitions/e2955ace-17ae-5371-9462-8a42150fab3d",
        "Name": "e2955ace-17ae-5371-9462-8a42150fab3d",
        "properties": {
          "assignableScopes": [
            "/providers/Microsoft.Management/managementGroups/mg-oqlf3"
          ],
          "description": "Enablement",
          "permissions": [
            {
              "actions": [
                "Microsoft.Insights/*",
                "Microsoft.Automation/automationAccounts/*",
                "Microsoft.Resources/subscriptions/resourceGroups/read",
                "Microsoft.Management/managementGroups/read",
                "Microsoft.Support/*"
              ],
              "dataActions": [],
              "notActions": [],
              "notdataActions": []
            }
          ],
          "roleName": "rbac-ass-oqlf3-IT-prod-Custom Enablement"
        },
        "ResourceType": "Microsoft.Authorization/roleDefinitions"
      }
    }
  }
}
